CHANGES.txt
MANIFEST.in
README.rst
setup.py
crib/__init__.py
crib/command.py
crib/crib.py
crib.egg-info/PKG-INFO
crib.egg-info/SOURCES.txt
crib.egg-info/dependency_links.txt
crib.egg-info/entry_points.txt
crib.egg-info/not-zip-safe
crib.egg-info/requires.txt
crib.egg-info/top_level.txt