Metadata-Version: 1.0
Name: crib
Version: 0.2.1
Summary: Minimal command line encryption for tiny notes
Home-page: http://github.com/lepisma/crib
Author: lepisma
Author-email: abhinav.tushar.vs@gmail.com
License: MIT
Keywords: notes encryption minimal
Platform: UNKNOWN
